coordinationz-0.1.2.dist-info/RECORD
coordinationz-0.1.2.dist-info/WHEEL
coordinationz-0.1.2.dist-info/METADATA
coordinationz/communities.py
coordinationz/experiment_utilities.py
coordinationz/config.py
coordinationz/__init__.py
coordinationz/visualization.py
coordinationz/textsimilarity_helper.py
coordinationz/cohashtag_helper.py
coordinationz/network.py
coordinationz/indicator_utilities.py
coordinationz/nullmodel.py
coordinationz/fastcosine_core.cpython-311-darwin.so
coordinationz/usc_text_similarity.py
coordinationz/fastcosine.py
coordinationz/preprocess_utilities.py
