Metadata-Version: 2.1
Name: coordinationz
Version: 0.1.2
Summary: Package to create networks for detecting coordination in social media.
Author-Email: "Filipi N. Silva" <filipinascimento@gmail.com>, Manita Pote <potem@iu.edu>, Lake Yin <lakeyin@iu.edu>, David Axelrod <daaxelro@iu.edu>, Luca Luceri <lluceri@isi.edu>, Ashwin Balasubramanian <ashwinb@isi.edu>
Classifier: Development Status :: 3 - Alpha
Classifier: Intended Audience :: Developers
Classifier: License :: OSI Approved :: MIT License
Classifier: Programming Language :: Python :: 3 :: Only
Classifier: Programming Language :: Python :: 3.8
Classifier: Programming Language :: Python :: 3.9
Classifier: Programming Language :: Python :: 3.10
Classifier: Programming Language :: Python :: 3.11
Project-URL: Documentation, https://github.com/filipinascimento/coordinationz
Project-URL: Source, https://github.com/filipinascimento/coordinationz
Project-URL: Tracker, https://github.com/filipinascimento/coordinationz/issues
Requires-Python: >=3.8.1
Requires-Dist: numpy
Requires-Dist: pandas
Requires-Dist: scipy
Requires-Dist: tqdm
Requires-Dist: toml
Requires-Dist: python-igraph
Requires-Dist: xnetwork
Requires-Dist: nltk
Requires-Dist: unalix
Requires-Dist: emoji
